[
  {
    "name": "11",
    "published_date": "1988-08-08",
    "last_played_at": "2009-09-09",
    "multiplayer": true,
    "author": {
      "first_name": "t",
      "last_name": "t"
    }
  },
  {
    "name": "hello",
    "published_date": "2005-05-05",
    "last_played_at": "2007-07-07",
    "multiplayer": true,
    "author": {
      "first_name": "yousef",
      "last_name": "no"
    }
  },
  {
    "name": "game2",
    "published_date": "2008-08-08",
    "last_played_at": "2007-07-07",
    "multiplayer": true,
    "author": {
      "first_name": "yousef",
      "last_name": "mo"
    }
  }
]